complimentr/__init__.py
complimentr/ask_user_for_info.py
complimentr/common.py
complimentr/compliments.py
complimentr/messageSender.py
complimentr/run_website.py
complimentr/settings.py
complimentr/tasks.py
complimentr-0.0.9.data/data/my_data/data_file
complimentr-0.0.9.dist-info/DESCRIPTION.rst
complimentr-0.0.9.dist-info/METADATA
complimentr-0.0.9.dist-info/RECORD
complimentr-0.0.9.dist-info/WHEEL
complimentr-0.0.9.dist-info/entry_points.txt
complimentr-0.0.9.dist-info/metadata.json
complimentr-0.0.9.dist-info/top_level.txt
